{
  "player 1": {
    "name" : "3drosalia",
    "UUID" : "3",
    "diff": 3,
    "inst": 2,
    "NoteSpeed": 1.5,
    "bot": true,
    "inputOffset": 0.0,
    "classic": true,
    "proDrums": true,
    "lefty": false
  },
  "player 2": {
    "name" : "lothycat",
    "UUID" : "6",
    "diff": 3,
    "inst": 2,
    "NoteSpeed": 1.5,
    "bot": true,
    "inputOffset": 0.0,
    "classic": true,
    "proDrums": true,
    "lefty": false
  },
  "player 3": {
    "name" : "JSON player 3",
    "UUID" : "1",
    "diff": 3,
    "inst": 2,
    "NoteSpeed": 1.5,
    "bot": true,
    "inputOffset": 0.0,
    "classic": true,
    "proDrums": true,
    "lefty": false
  }
}